{
  "best_metric": null,
  "best_model_checkpoint": null,
  "epoch": 2.4752475247524752,
  "global_step": 500,
  "is_hyper_param_search": false,
  "is_local_process_zero": true,
  "is_world_process_zero": true,
  "log_history": [
    {
      "epoch": 0.99,
      "learning_rate": 0.000466996699669967,
      "loss": 1.3255,
      "step": 200
    },
    {
      "epoch": 1.98,
      "learning_rate": 0.000433993399339934,
      "loss": 0.6355,
      "step": 400
    }
  ],
  "max_steps": 3030,
  "num_train_epochs": 15,
  "total_flos": 2134521432668160.0,
  "trial_name": null,
  "trial_params": null
}
